scicookie/__init__.py
scicookie/__main__.py
scicookie/cli.py
scicookie/cookiecutter.json
scicookie/hooks/post_gen_project.py
scicookie/hooks/pre_gen_project.py
scicookie/logs.py
scicookie/profile.py
scicookie/profiles/base.yaml
scicookie/profiles/osl.yaml
scicookie/tools/__init__.py
scicookie/tools/fix_eof.py
scicookie/ui.py
scicookie/{{cookiecutter.project_slug}}/.circleci/config.yml
scicookie/{{cookiecutter.project_slug}}/.editorconfig
scicookie/{{cookiecutter.project_slug}}/.github/ISSUE_TEMPLATE/bug-report.yml
scicookie/{{cookiecutter.project_slug}}/.github/ISSUE_TEMPLATE/config.yml
scicookie/{{cookiecutter.project_slug}}/.github/ISSUE_TEMPLATE/documentation-report.yml
scicookie/{{cookiecutter.project_slug}}/.github/ISSUE_TEMPLATE/feature-request.yml
scicookie/{{cookiecutter.project_slug}}/.github/PULL_REQUEST_TEMPLATE.md
scicookie/{{cookiecutter.project_slug}}/.github/workflows/main.yaml
scicookie/{{cookiecutter.project_slug}}/.github/workflows/release.yaml
scicookie/{{cookiecutter.project_slug}}/.gitignore
scicookie/{{cookiecutter.project_slug}}/.gitlab-ci.yml
scicookie/{{cookiecutter.project_slug}}/.makim.yaml
scicookie/{{cookiecutter.project_slug}}/.pre-commit-config.yaml
scicookie/{{cookiecutter.project_slug}}/.prettierignore
scicookie/{{cookiecutter.project_slug}}/.prettierrc.yaml
scicookie/{{cookiecutter.project_slug}}/.releaserc.json
scicookie/{{cookiecutter.project_slug}}/LICENSE
scicookie/{{cookiecutter.project_slug}}/Makefile
scicookie/{{cookiecutter.project_slug}}/README.md
scicookie/{{cookiecutter.project_slug}}/azure-pipelines.yml
scicookie/{{cookiecutter.project_slug}}/build-system/base/config-bandit.toml
scicookie/{{cookiecutter.project_slug}}/build-system/base/config-black.toml
scicookie/{{cookiecutter.project_slug}}/build-system/base/config-isort.toml
scicookie/{{cookiecutter.project_slug}}/build-system/base/config-mypy.toml
scicookie/{{cookiecutter.project_slug}}/build-system/base/config-pytest.toml
scicookie-0.12.0.dist-info/LICENSE
scicookie-0.12.0.dist-info/METADATA
scicookie-0.12.0.dist-info/WHEEL
scicookie-0.12.0.dist-info/entry_points.txt
scicookie-0.12.0.dist-info/RECORD
