Metadata-Version: 2.3
Name: scicookie
Version: 0.12.0
Summary: Cookiecutter template for a Python package
License: BSD-3-Clause
Author: Ivan Ogasawara
Author-email: ivan.ogasawara@gmail.com
Requires-Python: >=3.9,<4
Classifier: License :: OSI Approved :: BSD License
Classifier: Programming Language :: Python :: 3
Classifier: Programming Language :: Python :: 3.9
Classifier: Programming Language :: Python :: 3.10
Classifier: Programming Language :: Python :: 3.11
Classifier: Programming Language :: Python :: 3.12
Classifier: Programming Language :: Python :: 3.13
Requires-Dist: colorama (>=0.4.6)
Requires-Dist: cookiecutter (>=2.6.0)
Requires-Dist: inquirer (>=3.1.3)
Requires-Dist: nodejs-wheel (>=20.13.0-1)
Requires-Dist: pre-commit-hooks (>=0.4.6)
Requires-Dist: pyyaml (>=6.0.1)
